eggi/__init__.py
eggi/main.py
eggi-0.1.0.dist-info/LICENSE
eggi-0.1.0.dist-info/METADATA
eggi-0.1.0.dist-info/WHEEL
eggi-0.1.0.dist-info/RECORD
